unidic_lite_imitator_transformers/__init__.py
unidic_lite_imitator_transformers/config.json
unidic_lite_imitator_transformers/ma_imitator.py
unidic_lite_imitator_transformers/model.pth
unidic_lite_imitator_transformers-0.2.1.dist-info/LICENSE
unidic_lite_imitator_transformers-0.2.1.dist-info/METADATA
unidic_lite_imitator_transformers-0.2.1.dist-info/WHEEL
unidic_lite_imitator_transformers-0.2.1.dist-info/top_level.txt
unidic_lite_imitator_transformers-0.2.1.dist-info/RECORD
