Metadata-Version: 2.1
Name: unidic-lite-imitator-transformers
Version: 0.2.1
Summary: Imitate Japanese morphological analysis of mecab and unidic_lite with a small transformers model.
Author-email: Yutaka Nakano <nknytk.dev@gmail.com>
License: CC-BY-SA 3.0
Project-URL: Homepage, https://github.com/nknytk/ma-imitator
Project-URL: Bug Tracker, https://github.com/nknytk/ma-imitator/issues
Classifier: Development Status :: 4 - Beta
Classifier: Programming Language :: Python :: 3.8
Classifier: Programming Language :: Python :: 3.9
Classifier: Programming Language :: Python :: 3.10
Classifier: Programming Language :: Python :: 3.11
Classifier: Operating System :: OS Independent
Requires-Python: <=3.11,>=3.8
License-File: LICENSE
Requires-Dist: torch >=2.0.0
Requires-Dist: transformers >=4.21.0
